stok/__init__.py
stok/train.py
stok/checkpoints/codebook/base.pt
stok/checkpoints/codebook/lite.pt
stok/cli/cli.py
stok/cli/smoke_test.py
stok/cli/train.py
stok/configs/config.yaml
stok/configs/data/base.yaml
stok/configs/model/arch.yaml
stok/configs/train/base.yaml
stok/data/collate.py
stok/data/dataset.py
stok/models/attention.py
stok/models/blocks.py
stok/models/decoder.py
stok/models/encoder.py
stok/models/gcpnet.py
stok/models/head.py
stok/models/mlp.py
stok/models/rope.py
stok/models/stok.py
stok/utils/codebook.py
stok/utils/featurizer.py
stok/utils/gcp.py
stok/utils/geometry.py
stok/utils/losses.py
stok/utils/masking.py
stok/utils/pdb.py
stok/utils/sampling.py
stok/utils/tokenizer.py
stok-0.1.4.dist-info/licenses/LICENSE
stok-0.1.4.dist-info/METADATA
stok-0.1.4.dist-info/WHEEL
stok-0.1.4.dist-info/entry_points.txt
stok-0.1.4.dist-info/top_level.txt
stok-0.1.4.dist-info/RECORD
