Metadata-Version: 2.4
Name: stok
Version: 0.1.4
Summary: Encoder-only protein tagger (SDPA + RoPE + SwiGLU)
Author: Bryan Briney
License: MIT License
Requires-Python: >=3.10
License-File: LICENSE
Requires-Dist: torch
Requires-Dist: hydra-core
Requires-Dist: omegaconf
Requires-Dist: graphein
Requires-Dist: torch_geometric
Requires-Dist: click>=8.1
Requires-Dist: wandb
Requires-Dist: accelerate
Requires-Dist: tokenizers
Requires-Dist: numpy
Requires-Dist: pandas
Requires-Dist: biopython
Requires-Dist: transformers
Requires-Dist: x-transformers
Requires-Dist: typing-extensions; python_version < "3.11"
Dynamic: license-file
